canvas_protocol/__init__.py
canvas_protocol/client/main.py
canvas_protocol/client/parser.py
canvas_protocol/color/color.py
canvas_protocol/protocol/packing.py
canvas_protocol/protocol/requests.py
canvas_protocol/protocol/responses.py
canvas_protocol/py.typed
canvas_protocol/stats/stats.py
canvas_protocol-0.1.0.dist-info/WHEEL
canvas_protocol-0.1.0.dist-info/METADATA
canvas_protocol-0.1.0.dist-info/RECORD
